websiterecon/__init__.py
websiterecon/cli.py
websiterecon/scanner.py
websiterecon-0.1.6.dist-info/licenses/LICENSE
websiterecon-0.1.6.dist-info/METADATA
websiterecon-0.1.6.dist-info/WHEEL
websiterecon-0.1.6.dist-info/entry_points.txt
websiterecon-0.1.6.dist-info/top_level.txt
websiterecon-0.1.6.dist-info/RECORD
